{"code":0,"data":{"categories":[{"id":167618,"image":"shop-category-default-image.png","items":[{"adjust_price":0.0,"desc":"","first_commodity":"","first_commodity_id":"","group_buy":0,"group_price":0,"id":1788811,"image":"https://easi.com.au/static/uploads/photos/s3_a802915449b990299225d1963fbce9a7.jpg","images":["https://easi.com.au/static/uploads/photos/s3_a802915449b990299225d1963fbce9a7.jpg"],"is_multiple_sku":false,"is_registered_for_vat":1,"is_sku":1,"is_vat_included":0,"mark_text":"","name":"\u4ec0\u9526\u7f8a\u8089\u7092\u9762","option_groups":[],"org_price":13.5,"price":13.5,"second_commodity":"","second_commodity_id":"","seq":1,"shop_id":20447,"sku_id":8476462,"status":1,"stock":-1,"tobacco_alcohol":0,"unit":0,"update_time":"2019.12.22 15:35:28","vat_rate":0.0},{"adjust_price":0.0,"desc":"","first_commodity":"","first_commodity_id":"","group_buy":0,"group_price":0,"id":1788813,"image":"https://easi.com.au/static/uploads/photos/s3_c0630bffd3139d7cac9ab65ebd324bc0.jpg","images":["https://easi.com.au/static/uploads/photos/s3_c0630bffd3139d7cac9ab65ebd324bc0.jpg"],"is_multiple_sku":false,"is_registered_for_vat":1,"is_sku":1,"is_vat_included":0,"mark_text":"","name":"\u4ec0\u9526\u725b\u8089\u7092\u9762","option_groups":[],"org_price":13.5,"price":13.5,"second_commodity":"","second_commodity_id":"","seq":2,"shop_id":20447,"sku_id":8476465,"status":1,"stock":-1,"tobacco_alcohol":0,"unit":0,"update_time":"2019.12.22 15:35:28","vat_rate":0.0},{"adjust_price":0.0,"desc":"","first_commodity":"","first_commodity_id":"","group_buy":0,"group_price":0,"id":1788817,"image":"https://easi.com.au/static/uploads/photos/s3_3df17fd4c2f66e2b50de9dc5e072a6b6.jpg","images":["https://easi.com.au/static/uploads/photos/s3_3df17fd4c2f66e2b50de9dc5e072a6b6.jpg"],"is_multiple_sku":true,"is_registered_for_vat":1,"is_sku":1,"is_vat_included":0,"mark_text":"","name":"\u798f\u5efa\u7092\u9762","option_groups":[{"id":1868339,"limit":1,"min":0,"mode":0,"name":"Size","options":[{"adjust_price":0.0,"group_buy":0,"group_price":0,"id":8626353,"limit":0,"name":"\u9e21\u8089","option_group_id":1868339,"org_price":12.5,"price":12.5,"stock":-1,"type":"sku"},{"adjust_price":0.0,"group_buy":0,"group_price":0,"id":8626354,"limit":0,"name":"\u725b\u8089","option_group_id":1868339,"org_price":13.5,"price":13.5,"stock":-1,"type":"sku"},{"adjust_price":0.0,"group_buy":0,"group_price":0,"id":8626355,"limit":0,"name":"\u6d77\u9c9c","option_group_id":1868339,"org_price":13.5,"price":13.5,"stock":-1,"type":"sku"},{"adjust_price":0.0,"group_buy":0,"group_price":0,"id":8626356,"limit":0,"name":"\u7d20","option_group_id":1868339,"org_price":13.5,"price":13.5,"stock":-1,"type":"sku"}],"type":"sku"}],"org_price":12.5,"price":12.5,"second_commodity":"","second_commodity_id":"","seq":4,"shop_id":20447,"status":1,"stock":-1,"tobacco_alcohol":0,"unit":0,"update_time":"2019.12.22 15:35:28","vat_rate":0.0},{"adjust_price":0.0,"desc":"","first_commodity":"","first_commodity_id":"","group_buy":0,"group_price":0,"id":1788820,"image":"https://easi.com.au/static/uploads/photos/s3_f4252a85d878f2d39323a19554fc0731.jpg","images":["https://easi.com.au/static/uploads/photos/s3_f4252a85d878f2d39323a19554fc0731.jpg"],"is_multiple_sku":true,"is_registered_for_vat":1,"is_sku":1,"is_vat_included":0,"mark_text":"","name":"\u7092\u6cb3\u7c89","option_groups":[{"id":1868340,"limit":1,"min":0,"mode":0,"name":"Size","options":[{"adjust_price":0.0,"group_buy":0,"group_price":0,"id":8626357,"limit":0,"name":"\u9e21\u8089","option_group_id":1868340,"org_price":12.5,"price":12.5,"stock":-1,"type":"sku"},{"adjust_price":0.0,"group_buy":0,"group_price":0,"id":8626358,"limit":0,"name":"\u725b\u8089","option_group_id":1868340,"org_price":13.5,"price":13.5,"stock":-1,"type":"sku"},{"adjust_price":0.0,"group_buy":0,"group_price":0,"id":8626359,"limit":0,"name":"\u6d77\u9c9c","option_group_id":1868340,"org_price":13.5,"price":13.5,"stock":-1,"type":"sku"},{"adjust_price":0.0,"group_buy":0,"group_price":0,"id":8626360,"limit":0,"name":"\u7d20","option_group_id":1868340,"org_price":13.5,"price":13.5,"stock":-1,"type":"sku"}],"type":"sku"}],"org_price":12.5,"price":12.5,"second_commodity":"","second_commodity_id":"","seq":5,"shop_id":20447,"status":1,"stock":-1,"tobacco_alcohol":0,"unit":0,"update_time":"2019.12.22 15:35:28","vat_rate":0.0}],"name":"\u624b\u62c9\u9762","seq":2,"shop_id":20447},{"id":167630,"image":"shop-category-default-image.png","items":[{"adjust_price":0.0,"desc":"","first_commodity":"","first_commodity_id":"","group_buy":0,"group_price":0,"id":1788822,"image":"https://easi.com.au/static/uploads/photos/s3_9dacf448c03ebae320f64e47981fecf2.jpg","images":["https://easi.com.au/static/uploads/photos/s3_9dacf448c03ebae320f64e47981fecf2.jpg"],"is_multiple_sku":false,"is_registered_for_vat":1,"is_sku":1,"is_vat_included":0,"mark_text":"","name":"\u8471\u7206\u7f8a\u8089\u996d","option_groups":[],"org_price":14.5,"price":14.5,"second_commodity":"","second_commodity_id":"","seq":6,"shop_id":20447,"sku_id":8476529,"status":1,"stock":-1,"tobacco_alcohol":0,"unit":0,"update_time":"2019.12.22 15:35:28","vat_rate":0.0},{"adjust_price":0.0,"desc":"","first_commodity":"","first_commodity_id":"","group_buy":0,"group_price":0,"id":1788824,"image":"https://easi.com.au/static/uploads/photos/s3_d8b1f4b10cb6d969d2f1a2e425f98656.jpg","images":["https://easi.com.au/static/uploads/photos/s3_d8b1f4b10cb6d969d2f1a2e425f98656.jpg"],"is_multiple_sku":false,"is_registered_for_vat":1,"is_sku":1,"is_vat_included":0,"mark_text":"","name":"\u8471\u7206\u725b\u8089\u996d","option_groups":[],"org_price":14.5,"price":14.5,"second_commodity":"","second_commodity_id":"","seq":7,"shop_id":20447,"sku_id":8476534,"status":1,"stock":-1,"tobacco_alcohol":0,"unit":0,"update_time":"2019.12.22 15:35:28","vat_rate":0.0},{"adjust_price":0.0,"desc":"","first_commodity":"","first_commodity_id":"","group_buy":0,"group_price":0,"id":1788826,"image":"https://easi.com.au/static/uploads/photos/s3_436adb9d038f7892fd413254e7d8e321.jpg","images":["https://easi.com.au/static/uploads/photos/s3_436adb9d038f7892fd413254e7d8e321.jpg"],"is_multiple_sku":false,"is_registered_for_vat":1,"is_sku":1,"is_vat_included":0,"mark_text":"","name":"\u7206\u7092\u7f8a\u809a\u996d","option_groups":[],"org_price":13.5,"price":13.5,"second_commodity":"","second_commodity_id":"","seq":8,"shop_id":20447,"sku_id":8476592,"status":1,"stock":-1,"tobacco_alcohol":0,"unit":0,"update_time":"2019.12.22 15:35:28","vat_rate":0.0},{"adjust_price":0.0,"desc":"","first_commodity":"","first_commodity_id":"","group_buy":0,"group_price":0,"id":1788828,"image":"https://easi.com.au/static/uploads/photos/s3_e5445b995f9fe4f3790168b6a6fd2141.jpg","images":["https://easi.com.au/static/uploads/photos/s3_e5445b995f9fe4f3790168b6a6fd2141.jpg"],"is_multiple_sku":false,"is_registered_for_vat":1,"is_sku":1,"is_vat_included":0,"mark_text":"","name":"\u7ea2\u7116\u7f8a\u6392\u996d","option_groups":[],"org_price":13.5,"price":13.5,"second_commodity":"","second_commodity_id":"","seq":9,"shop_id":20447,"sku_id":8476625,"status":1,"stock":-1,"tobacco_alcohol":0,"unit":0,"update_time":"2019.12.22 15:35:28","vat_rate":0.0},{"adjust_price":0.0,"desc":"","first_commodity":"","first_commodity_id":"","group_buy":0,"group_price":0,"id":1788830,"image":"https://easi.com.au/static/uploads/photos/s3_e9023551dc42ac69795c931755f99f5c.jpg","images":["https://easi.com.au/static/uploads/photos/s3_e9023551dc42ac69795c931755f99f5c.jpg"],"is_multiple_sku":false,"is_registered_for_vat":1,"is_sku":1,"is_vat_included":0,"mark_text":"","name":"\u7206\u7092\u56de\u9505\u8089\u996d","option_groups":[],"org_price":13.5,"price":13.5,"second_commodity":"","second_commodity_id":"","seq":10,"shop_id":20447,"sku_id":8476629,"status":1,"stock":-1,"tobacco_alcohol":0,"unit":0,"update_time":"2019.12.22 15:35:28","vat_rate":0.0},{"adjust_price":0.0,"desc":"","first_commodity":"","first_commodity_id":"","group_buy":0,"group_price":0,"id":1788832,"image":"https://easi.com.au/static/uploads/photos/s3_984a13ca7feb918a9dd7630a020ecc64.jpg","images":["https://easi.com.au/static/uploads/photos/s3_984a13ca7feb918a9dd7630a020ecc64.jpg"],"is_multiple_sku":false,"is_registered_for_vat":1,"is_sku":1,"is_vat_included":0,"mark_text":"","name":"\u4e94\u82b1\u8089\u9178\u83dc\u996d","option_groups":[],"org_price":13.5,"price":13.5,"second_commodity":"","second_commodity_id":"","seq":11,"shop_id":20447,"sku_id":8476637,"status":1,"stock":-1,"tobacco_alcohol":0,"unit":0,"update_time":"2019.12.22 15:35:28","vat_rate":0.0},{"adjust_price":0.0,"desc":"","first_commodity":"","first_commodity_id":"","group_buy":0,"group_price":0,"id":1788834,"image":"https://easi.com.au/static/uploads/photos/s3_5b0f6a19906540800bf1997465699345.jpg","images":["https://easi.com.au/static/uploads/photos/s3_5b0f6a19906540800bf1997465699345.jpg"],"is_multiple_sku":false,"is_registered_for_vat":1,"is_sku":1,"is_vat_included":0,"mark_text":"","name":"\u9752\u6912\u8089\u4e1d\u996d","option_groups":[],"org_price":13.5,"price":13.5,"second_commodity":"","second_commodity_id":"","seq":12,"shop_id":20447,"sku_id":8476645,"status":1,"stock":-1,"tobacco_alcohol":0,"unit":0,"update_time":"2019.12.22 15:35:28","vat_rate":0.0},{"adjust_price":0.0,"desc":"","first_commodity":"","first_commodity_id":"","group_buy":0,"group_price":0,"id":1788835,"image":"https://easi.com.au/static/uploads/photos/s3_22e01ed3c05c9efd8a8247d8b75d27be.jpg","images":["https://easi.com.au/static/uploads/photos/s3_22e01ed3c05c9efd8a8247d8b75d27be.jpg"],"is_multiple_sku":false,"is_registered_for_vat":1,"is_sku":1,"is_vat_included":0,"mark_text":"","name":"\u8fa3\u6912\u9e21\u4e1d\u996d","option_groups":[],"org_price":13.5,"price":13.5,"second_commodity":"","second_commodity_id":"","seq":13,"shop_id":20447,"sku_id":8476652,"status":1,"stock":-1,"tobacco_alcohol":0,"unit":0,"update_time":"2019.12.22 15:35:28","vat_rate":0.0},{"adjust_price":0.0,"desc":"","first_commodity":"","first_commodity_id":"","group_buy":0,"group_price":0,"id":1788837,"image":"https://easi.com.au/static/uploads/photos/s3_5e27e8f561cf54bb1837e773e0d3c4f2.jpg","images":["https://easi.com.au/static/uploads/photos/s3_5e27e8f561cf54bb1837e773e0d3c4f2.jpg"],"is_multiple_sku":false,"is_registered_for_vat":1,"is_sku":1,"is_vat_included":0,"mark_text":"","name":"\u5c16\u6912\u725b\u8089\u996d","option_groups":[],"org_price":13.5,"price":13.5,"second_commodity":"","second_commodity_id":"","seq":14,"shop_id":20447,"sku_id":8476659,"status":1,"stock":-1,"tobacco_alcohol":0,"unit":0,"update_time":"2019.12.22 15:35:28","vat_rate":0.0},{"adjust_price":0.0,"desc":"","first_commodity":"","first_commodity_id":"","group_buy":0,"group_price":0,"id":1788839,"image":"https://easi.com.au/static/uploads/photos/s3_e01489cffb97846df61c6e285f992e03.jpg","images":["https://easi.com.au/static/uploads/photos/s3_e01489cffb97846df61c6e285f992e03.jpg"],"is_multiple_sku":false,"is_registered_for_vat":1,"is_sku":1,"is_vat_included":0,"mark_text":"","name":"\u9ebb\u8fa3\u9c7c\u7247\u996d","option_groups":[],"org_price":13.5,"price":13.5,"second_commodity":"","second_commodity_id":"","seq":15,"shop_id":20447,"sku_id":8476682,"status":1,"stock":-1,"tobacco_alcohol":0,"unit":0,"update_time":"2019.12.22 15:35:28","vat_rate":0.0},{"adjust_price":0.0,"desc":"","first_commodity":"","first_commodity_id":"","group_buy":0,"group_price":0,"id":1788840,"image":"https://easi.com.au/static/uploads/photos/s3_35950b8ac0830db0cd6e7ad1e05463bb.jpg","images":["https://easi.com.au/static/uploads/photos/s3_35950b8ac0830db0cd6e7ad1e05463bb.jpg"],"is_multiple_sku":false,"is_registered_for_vat":1,"is_sku":1,"is_vat_included":0,"mark_text":"","name":"\u8fa3\u5b50\u80a5\u80a0\u996d","option_groups":[],"org_price":14.5,"price":14.5,"second_commodity":"","second_commodity_id":"","seq":16,"shop_id":20447,"sku_id":8626363,"status":1,"stock":-1,"tobacco_alcohol":0,"unit":0,"update_time":"2019.12.22 15:35:28","vat_rate":0.0},{"adjust_price":0.0,"desc":"","first_commodity":"","first_commodity_id":"","group_buy":0,"group_price":0,"id":1788843,"image":"https://easi.com.au/static/uploads/photos/s3_4ab590b7b9a93b703c2a71de02677b28.jpg","images":["https://easi.com.au/static/uploads/photos/s3_4ab590b7b9a93b703c2a71de02677b28.jpg"],"is_multiple_sku":false,"is_registered_for_vat":1,"is_sku":1,"is_vat_included":0,"mark_text":"","name":"\u897f\u5170\u82b1\u5927\u867e\u996d","option_groups":[],"org_price":14.5,"price":14.5,"second_commodity":"","second_commodity_id":"","seq":17,"shop_id":20447,"sku_id":8476690,"status":1,"stock":-1,"tobacco_alcohol":0,"unit":0,"update_time":"2019.12.22 15:35:28","vat_rate":0.0},{"adjust_price":0.0,"desc":"","first_commodity":"","first_commodity_id":"","group_buy":0,"group_price":0,"id":1788845,"image":"https://easi.com.au/static/uploads/photos/s3_e32da6c02ee56d5530ea1d1fbc252ea8.jpg","images":["https://easi.com.au/static/uploads/photos/s3_e32da6c02ee56d5530ea1d1fbc252ea8.jpg"],"is_multiple_sku":false,"is_registered_for_vat":1,"is_sku":1,"is_vat_included":0,"mark_text":"","name":"\u8499\u53e4\u725b\u8089\u996d","option_groups":[],"org_price":13.5,"price":13.5,"second_commodity":"","second_commodity_id":"","seq":18,"shop_id":20447,"sku_id":8476697,"status":1,"stock":-1,"tobacco_alcohol":0,"unit":0,"update_time":"2019.12.22 15:35:28","vat_rate":0.0},{"adjust_price":0.0,"desc":"","first_commodity":"","first_commodity_id":"","group_buy":0,"group_price":0,"id":1788846,"image":"https://easi.com.au/static/uploads/photos/s3_cf9586652cbcd8a5981a6d718b03710f.jpg","images":["https://easi.com.au/static/uploads/photos/s3_cf9586652cbcd8a5981a6d718b03710f.jpg"],"is_multiple_sku":false,"is_registered_for_vat":1,"is_sku":1,"is_vat_included":0,"mark_text":"","name":"\u8c49\u6c41\u725b\u8089\u996d","option_groups":[],"org_price":13.5,"price":13.5,"second_commodity":"","second_commodity_id":"","seq":19,"shop_id":20447,"sku_id":8476700,"status":1,"stock":-1,"tobacco_alcohol":0,"unit":0,"update_time":"2019.12.22 15:35:28","vat_rate":0.0},{"adjust_price":0.0,"desc":"","first_commodity":"","first_commodity_id":"","group_buy":0,"group_price":0,"id":1788849,"image":"https://easi.com.au/static/uploads/photos/s3_f3453e91df77b79325ba94067ebb7294.jpg","images":["https://easi.com.au/static/uploads/photos/s3_f3453e91df77b79325ba94067ebb7294.jpg"],"is_multiple_sku":false,"is_registered_for_vat":1,"is_sku":1,"is_vat_included":0,"mark_text":"","name":"\u65f6\u83dc\u725b\u8089\u996d","option_groups":[],"org_price":12.5,"price":12.5,"second_commodity":"","second_commodity_id":"","seq":20,"shop_id":20447,"sku_id":8626361,"status":1,"stock":-1,"tobacco_alcohol":0,"unit":0,"update_time":"2019.12.22 15:35:28","vat_rate":0.0},{"adjust_price":0.0,"desc":"","first_commodity":"","first_commodity_id":"","group_buy":0,"group_price":0,"id":1788850,"image":"https://easi.com.au/static/uploads/photos/s3_94144393abe73f6430754747607bee04.jpg","images":["https://easi.com.au/static/uploads/photos/s3_94144393abe73f6430754747607bee04.jpg"],"is_multiple_sku":false,"is_registered_for_vat":1,"is_sku":1,"is_vat_included":0,"mark_text":"","name":"\u65f6\u83dc\u9e21\u4e01\u996d","option_groups":[],"org_price":12.5,"price":12.5,"second_commodity":"","second_commodity_id":"","seq":21,"shop_id":20447,"sku_id":8626362,"status":1,"stock":-1,"tobacco_alcohol":0,"unit":0,"update_time":"2019.12.22 15:35:28","vat_rate":0.0},{"adjust_price":0.0,"desc":"","first_commodity":"","first_commodity_id":"","group_buy":0,"group_price":0,"id":1803675,"image":"","images":[],"is_multiple_sku":false,"is_registered_for_vat":1,"is_sku":1,"is_vat_included":0,"mark_text":"","name":"\u989d\u5916\u52a0\u7c73\u996d","option_groups":[],"org_price":2.5,"price":2.5,"second_commodity":"","second_commodity_id":"","seq":33,"shop_id":20447,"sku_id":8699248,"status":1,"stock":-1,"tobacco_alcohol":0,"unit":0,"update_time":"2019.12.28 20:24:21","vat_rate":0.1}],"name":"\u7c73\u996d\u7c7b","seq":3,"shop_id":20447},{"id":167631,"image":"shop-category-default-image.png","items":[{"adjust_price":0.0,"desc":"","first_commodity":"","first_commodity_id":"","group_buy":0,"group_price":0,"id":1788853,"image":"https://easi.com.au/static/uploads/photos/s3_0b55d8d70ae3d4828cab9309a2d76b34.jpg","images":["https://easi.com.au/static/uploads/photos/s3_0b55d8d70ae3d4828cab9309a2d76b34.jpg"],"is_multiple_sku":false,"is_registered_for_vat":1,"is_sku":1,"is_vat_included":0,"mark_text":"","name":"\u751f\u7092\u9e21\u8089\u996d","option_groups":[],"org_price":11.5,"price":11.5,"second_commodity":"","second_commodity_id":"","seq":22,"shop_id":20447,"sku_id":8476711,"status":1,"stock":-1,"tobacco_alcohol":0,"unit":0,"update_time":"2019.12.22 15:35:28","vat_rate":0.0},{"adjust_price":0.0,"desc":"","first_commodity":"","first_commodity_id":"","group_buy":0,"group_price":0,"id":1788855,"image":"https://easi.com.au/static/uploads/photos/s3_171dc379ac695a26658f39bd62599ee8.jpg","images":["https://easi.com.au/static/uploads/photos/s3_171dc379ac695a26658f39bd62599ee8.jpg"],"is_multiple_sku":false,"is_registered_for_vat":1,"is_sku":1,"is_vat_included":0,"mark_text":"","name":"\u751f\u7092\u725b\u8089\u996d","option_groups":[],"org_price":11.5,"price":11.5,"second_commodity":"","second_commodity_id":"","seq":23,"shop_id":20447,"sku_id":8476800,"status":1,"stock":-1,"tobacco_alcohol":0,"unit":0,"update_time":"2019.12.22 15:35:28","vat_rate":0.0},{"adjust_price":0.0,"desc":"","first_commodity":"","first_commodity_id":"","group_buy":0,"group_price":0,"id":1788857,"image":"https://easi.com.au/static/uploads/photos/s3_2f16f07757019a9c54ec61d4fb57ad5e.jpg","images":["https://easi.com.au/static/uploads/photos/s3_2f16f07757019a9c54ec61d4fb57ad5e.jpg"],"is_multiple_sku":false,"is_registered_for_vat":1,"is_sku":1,"is_vat_included":0,"mark_text":"","name":"\u867e\u7092\u996d","option_groups":[],"org_price":11.5,"price":11.5,"second_commodity":"","second_commodity_id":"","seq":24,"shop_id":20447,"sku_id":8476863,"status":1,"stock":-1,"tobacco_alcohol":0,"unit":0,"update_time":"2019.12.22 15:35:28","vat_rate":0.0},{"adjust_price":0.0,"desc":"","first_commodity":"","first_commodity_id":"","group_buy":0,"group_price":0,"id":1788858,"image":"https://easi.com.au/static/uploads/photos/s3_4ad58a1463e542db92f50ea77257a4a5.jpg","images":["https://easi.com.au/static/uploads/photos/s3_4ad58a1463e542db92f50ea77257a4a5.jpg"],"is_multiple_sku":false,"is_registered_for_vat":1,"is_sku":1,"is_vat_included":0,"mark_text":"","name":"\u7d20\u7092\u996d","option_groups":[],"org_price":11.5,"price":11.5,"second_commodity":"","second_commodity_id":"","seq":25,"shop_id":20447,"sku_id":8476865,"status":1,"stock":-1,"tobacco_alcohol":0,"unit":0,"update_time":"2019.12.22 15:35:28","vat_rate":0.0}],"name":"\u7092\u996d\u7c7b","seq":4,"shop_id":20447},{"id":167632,"image":"shop-category-default-image.png","items":[{"adjust_price":0.0,"desc":"","first_commodity":"","first_commodity_id":"","group_buy":0,"group_price":0,"id":1788860,"image":"https://easi.com.au/static/uploads/photos/s3_735c009f8ad3178e303daed9cacc7621.jpg","images":["https://easi.com.au/static/uploads/photos/s3_735c009f8ad3178e303daed9cacc7621.jpg"],"is_multiple_sku":false,"is_registered_for_vat":1,"is_sku":1,"is_vat_included":0,"mark_text":"","name":"\u732a\u8089\u6c34\u997a","option_groups":[],"org_price":11.5,"price":11.5,"second_commodity":"","second_commodity_id":"","seq":27,"shop_id":20447,"sku_id":8476904,"status":1,"stock":-1,"tobacco_alcohol":0,"unit":0,"update_time":"2019.12.22 15:35:28","vat_rate":0.0},{"adjust_price":0.0,"desc":"","first_commodity":"","first_commodity_id":"","group_buy":0,"group_price":0,"id":1788861,"image":"https://easi.com.au/static/uploads/photos/s3_1672adb30b961560988d2abd51952bec.jpg","images":["https://easi.com.au/static/uploads/photos/s3_1672adb30b961560988d2abd51952bec.jpg"],"is_multiple_sku":false,"is_registered_for_vat":1,"is_sku":1,"is_vat_included":0,"mark_text":"","name":"\u7d20\u6c34\u997a","option_groups":[],"org_price":11.5,"price":11.5,"second_commodity":"","second_commodity_id":"","seq":28,"shop_id":20447,"sku_id":8476922,"status":1,"stock":-1,"tobacco_alcohol":0,"unit":0,"update_time":"2019.12.22 15:35:28","vat_rate":0.0},{"adjust_price":0.0,"desc":"","first_commodity":"","first_commodity_id":"","group_buy":0,"group_price":0,"id":1788863,"image":"https://easi.com.au/static/uploads/photos/s3_75b525c88b9f9cc0c161df52059c7cf8.jpg","images":["https://easi.com.au/static/uploads/photos/s3_75b525c88b9f9cc0c161df52059c7cf8.jpg"],"is_multiple_sku":false,"is_registered_for_vat":1,"is_sku":1,"is_vat_included":0,"mark_text":"","name":"\u9e21\u8089\u9c9c\u867e\u6c34\u997a","option_groups":[],"org_price":11.5,"price":11.5,"second_commodity":"","second_commodity_id":"","seq":29,"shop_id":20447,"sku_id":8476924,"status":1,"stock":-1,"tobacco_alcohol":0,"unit":0,"update_time":"2019.12.22 15:35:28","vat_rate":0.0}],"name":"\u997a\u5b50\u7c7b","seq":5,"shop_id":20447},{"id":167633,"image":"shop-category-default-image.png","items":[{"adjust_price":0.0,"desc":"","first_commodity":"","first_commodity_id":"","group_buy":0,"group_price":0,"id":1788864,"image":"https://easi.com.au/static/uploads/photos/s3_2802e5bf29a5e5a007c80f552aaa8f47.jpg","images":["https://easi.com.au/static/uploads/photos/s3_2802e5bf29a5e5a007c80f552aaa8f47.jpg"],"is_multiple_sku":false,"is_registered_for_vat":1,"is_sku":1,"is_vat_included":0,"mark_text":"","name":"\u732a\u8089\u9505\u8d34","option_groups":[],"org_price":11.5,"price":11.5,"second_commodity":"","second_commodity_id":"","seq":30,"shop_id":20447,"sku_id":8476969,"status":1,"stock":-1,"tobacco_alcohol":0,"unit":0,"update_time":"2019.12.22 15:35:28","vat_rate":0.0},{"adjust_price":0.0,"desc":"","first_commodity":"","first_commodity_id":"","group_buy":0,"group_price":0,"id":1788865,"image":"https://easi.com.au/static/uploads/photos/s3_be5b83789853eae043888aeb63b46eb3.jpg","images":["https://easi.com.au/static/uploads/photos/s3_be5b83789853eae043888aeb63b46eb3.jpg"],"is_multiple_sku":false,"is_registered_for_vat":1,"is_sku":1,"is_vat_included":0,"mark_text":"","name":"\u9e21\u867e\u9505\u8d34","option_groups":[],"org_price":11.5,"price":11.5,"second_commodity":"","second_commodity_id":"","seq":31,"shop_id":20447,"sku_id":8476971,"status":1,"stock":-1,"tobacco_alcohol":0,"unit":0,"update_time":"2019.12.22 15:35:28","vat_rate":0.0},{"adjust_price":0.0,"desc":"","first_commodity":"","first_commodity_id":"","group_buy":0,"group_price":0,"id":1788866,"image":"https://easi.com.au/static/uploads/photos/s3_0b026dc6641afc481ca9397a388a1308.jpg","images":["https://easi.com.au/static/uploads/photos/s3_0b026dc6641afc481ca9397a388a1308.jpg"],"is_multiple_sku":false,"is_registered_for_vat":1,"is_sku":1,"is_vat_included":0,"mark_text":"","name":"\u7d20\u9505\u8d34","option_groups":[],"org_price":11.5,"price":11.5,"second_commodity":"","second_commodity_id":"","seq":32,"shop_id":20447,"sku_id":8477000,"status":1,"stock":-1,"tobacco_alcohol":0,"unit":0,"update_time":"2019.12.22 15:35:28","vat_rate":0.0}],"name":"\u751f\u714e\u9505\u8d34","seq":6,"shop_id":20447}],"shop_info":{"addr":"27d Moonta Street, Adelaide SA, Australia","addr_remark":"","allow_pickup":1,"average_amount":null,"avg_score":0.0,"brief_info":"","business":0,"business_info":{"is_business":false,"is_can_make_order":false,"text":"Today 12:00 Open for business"},"cash_discount":null,"contact_number":"0882121917","coupons":[],"currency_symbol":"$","delivery_fee_discount":0.0,"delivery_fee_discount_condition":0.0,"delivery_fee_discount_type":0,"delivery_type":0,"desc":"","discount":0.165,"discount_type":1,"distance_text":"45 Mins Delivery","exclusive":null,"has_coupon":false,"has_delivery_fee_discount":0,"has_discount":false,"hot_sale":null,"id":20447,"image":"https://easi.com.au/static/uploads/photos/s3_f5e65f4023ce11ea91990a70f4cdf10a.jpg","is_self_pick":true,"is_support_delivery":true,"is_third_delivery_fee":false,"is_vat_included":true,"location":"-34.9301307,138.5959196","merchant_coupon":{"items":[],"total_fee":0},"name":"\u946b\u60a6\u65b0\u7586\u98ce\u5473","new_arrival":null,"next_business_time":"Today 12:00 ","payment_info":{"payment_type":1,"payment_type_name":"Pay Online"},"pickup_type":0,"platform_settlement_status":null,"points":0.0,"points_text":"","ratings":null,"real_contact_number":"0882121917","recommend":null,"reviews_count":0,"seq":1002666,"shop_area_id":26,"shop_order_fee_discount":0.0,"shop_style_id":51,"shop_type":"restaurant","threshold_amount":0.0,"today_business_time":"12:00 - 21:00","type":1,"update_time":"2020.04.07 17:20:30","vat_rate":0.1}}}
