{"code":0,"data":{"categories":[{"id":51192,"image":"shop-category-default-image.png","items":[{"adjust_price":0.0,"desc":"","first_commodity":"","first_commodity_id":"","group_buy":0,"group_price":0,"id":1228113,"image":"https://easi.com.au/static/uploads/photos/s3_b7f338c2794a11e982ed02531fff5ae4.jpg","images":["https://easi.com.au/static/uploads/photos/s3_b7f338c2794a11e982ed02531fff5ae4.jpg"],"is_multiple_sku":false,"is_registered_for_vat":1,"is_sku":1,"is_vat_included":1,"mark_text":"","name":"\u6cb9\u7116\u5c0f\u9f99\u867e 500g","option_groups":[],"org_price":38.0,"price":38.0,"second_commodity":"","second_commodity_id":"","seq":20,"shop_id":5493,"sku_id":6510861,"status":1,"stock":987,"tobacco_alcohol":0,"unit":0,"update_time":"2019.10.07 22:38:03","vat_rate":0.1},{"adjust_price":0.0,"desc":"","first_commodity":"","first_commodity_id":"","group_buy":0,"group_price":0,"id":1228114,"image":"https://easi.com.au/static/uploads/photos/s3_bfe5bfe6794a11e9a6790abd92605ac8.jpg","images":["https://easi.com.au/static/uploads/photos/s3_bfe5bfe6794a11e9a6790abd92605ac8.jpg"],"is_multiple_sku":false,"is_registered_for_vat":1,"is_sku":1,"is_vat_included":1,"mark_text":"","name":"\u6cb9\u7116\u5c0f\u9f99\u867e 1kg","option_groups":[],"org_price":68.0,"price":68.0,"second_commodity":"","second_commodity_id":"","seq":21,"shop_id":5493,"sku_id":6510862,"status":1,"stock":997,"tobacco_alcohol":0,"unit":0,"update_time":"2019.10.07 22:38:03","vat_rate":0.1},{"adjust_price":0.0,"desc":"","first_commodity":"","first_commodity_id":"","group_buy":0,"group_price":0,"id":1298297,"image":"https://easi.com.au/static/uploads/photos/s3_892fd84c794a11e9ac4f027362f1b176.jpg","images":["https://easi.com.au/static/uploads/photos/s3_892fd84c794a11e9ac4f027362f1b176.jpg"],"is_multiple_sku":false,"is_registered_for_vat":1,"is_sku":1,"is_vat_included":1,"mark_text":"","name":"\u849c\u9999\u5c0f\u9f99\u867e 500g","option_groups":[],"org_price":38.0,"price":38.0,"second_commodity":"","second_commodity_id":"","seq":23,"shop_id":5493,"sku_id":6510863,"status":1,"stock":990,"tobacco_alcohol":0,"unit":0,"update_time":"2019.10.07 22:38:03","vat_rate":0.1},{"adjust_price":0.0,"desc":"","first_commodity":"","first_commodity_id":"","group_buy":0,"group_price":0,"id":1298298,"image":"https://easi.com.au/static/uploads/photos/s3_a622a10a794a11e9bf9d02e7e60d917c.jpg","images":["https://easi.com.au/static/uploads/photos/s3_a622a10a794a11e9bf9d02e7e60d917c.jpg"],"is_multiple_sku":false,"is_registered_for_vat":1,"is_sku":1,"is_vat_included":1,"mark_text":"","name":"\u849c\u9999\u5c0f\u9f99\u867e 1kg","option_groups":[],"org_price":68.0,"price":68.0,"second_commodity":"","second_commodity_id":"","seq":24,"shop_id":5493,"sku_id":6510864,"status":1,"stock":995,"tobacco_alcohol":0,"unit":0,"update_time":"2019.10.07 22:38:03","vat_rate":0.1},{"adjust_price":0.0,"desc":"","first_commodity":"","first_commodity_id":"","group_buy":0,"group_price":0,"id":497206,"image":"https://easi.com.au/static/uploads/photos/s3_5e9ec4909665558e980c35e9d74257ef.jpg","images":["https://easi.com.au/static/uploads/photos/s3_5e9ec4909665558e980c35e9d74257ef.jpg"],"is_multiple_sku":false,"is_registered_for_vat":1,"is_sku":1,"is_vat_included":1,"mark_text":"","name":"Original Flavor Fried Chicken","option_groups":[],"org_price":19.8,"price":19.8,"second_commodity":"","second_commodity_id":"","seq":10010,"shop_id":5493,"sku_id":12753053,"status":1,"stock":942,"tobacco_alcohol":0,"unit":0,"update_time":"2019.10.07 22:38:03","vat_rate":0.1},{"adjust_price":0.0,"desc":"","first_commodity":"","first_commodity_id":"","group_buy":0,"group_price":0,"id":497209,"image":"https://easi.com.au/static/uploads/photos/s3_19c6ef160cef186037f2bac0726dd23f.jpg","images":["https://easi.com.au/static/uploads/photos/s3_19c6ef160cef186037f2bac0726dd23f.jpg"],"is_multiple_sku":false,"is_registered_for_vat":1,"is_sku":1,"is_vat_included":1,"mark_text":"","name":"\u97e9\u5f0f\u70b8\u9e21","option_groups":[],"org_price":19.8,"price":19.8,"second_commodity":"","second_commodity_id":"","seq":10010,"shop_id":5493,"sku_id":12753054,"status":1,"stock":911,"tobacco_alcohol":0,"unit":0,"update_time":"2019.10.07 22:38:03","vat_rate":0.1},{"adjust_price":0.0,"desc":"","first_commodity":"","first_commodity_id":"","group_buy":0,"group_price":0,"id":497210,"image":"https://easi.com.au/static/uploads/photos/s3_4277535d8f14e5530d45569e445595cb.jpg","images":["https://easi.com.au/static/uploads/photos/s3_4277535d8f14e5530d45569e445595cb.jpg"],"is_multiple_sku":false,"is_registered_for_vat":1,"is_sku":1,"is_vat_included":1,"mark_text":"","name":"\u5927\u962a\u70e7\u70b8\u9e21","option_groups":[],"org_price":19.8,"price":19.8,"second_commodity":"","second_commodity_id":"","seq":10012,"shop_id":5493,"sku_id":12753055,"status":1,"stock":947,"tobacco_alcohol":0,"unit":0,"update_time":"2019.10.07 22:38:03","vat_rate":0.1},{"adjust_price":0.0,"desc":"","first_commodity":"","first_commodity_id":"","group_buy":0,"group_price":0,"id":915015,"image":"https://easi.com.au/static/uploads/photos/p_20181030193046716081.jpg","images":["https://easi.com.au/static/uploads/photos/p_20181030193046716081.jpg"],"is_multiple_sku":false,"is_registered_for_vat":1,"is_sku":1,"is_vat_included":1,"mark_text":"","name":"\u4f60\u4ece\u672a\u5403\u8fc7\u7684\u7092\u62c9\u9762","option_groups":[],"org_price":15.8,"price":15.8,"second_commodity":"","second_commodity_id":"","seq":10014,"shop_id":5493,"sku_id":6510872,"status":1,"stock":942,"tobacco_alcohol":0,"unit":0,"update_time":"2019.10.07 22:38:03","vat_rate":0.1}],"name":"\u70ed\u9500\u65b0\u54c1","seq":2,"shop_id":5493},{"id":92235,"image":"shop-category-default-image.png","items":[{"adjust_price":0.0,"desc":"","first_commodity":"","first_commodity_id":"","group_buy":0,"group_price":0,"id":915033,"image":"https://easi.com.au/static/uploads/photos/p_20181030210102613211.jpg","images":["https://easi.com.au/static/uploads/photos/p_20181030210102613211.jpg"],"is_multiple_sku":false,"is_registered_for_vat":1,"is_sku":1,"is_vat_included":1,"mark_text":"","name":"\u90e8\u961f\u9505","option_groups":[],"org_price":38.0,"price":38.0,"second_commodity":"","second_commodity_id":"","seq":1,"shop_id":5493,"sku_id":6510886,"status":1,"stock":973,"tobacco_alcohol":0,"unit":0,"update_time":"2019.10.07 22:38:03","vat_rate":0.1},{"adjust_price":0.0,"desc":"","first_commodity":"","first_commodity_id":"","group_buy":0,"group_price":0,"id":915038,"image":"https://easi.com.au/static/uploads/photos/p_20181030210259280930.jpg","images":["https://easi.com.au/static/uploads/photos/p_20181030210259280930.jpg"],"is_multiple_sku":false,"is_registered_for_vat":1,"is_sku":1,"is_vat_included":1,"mark_text":"","name":"\u6d77\u9c9c\u8c46\u8150\u9505","option_groups":[],"org_price":58.0,"price":58.0,"second_commodity":"","second_commodity_id":"","seq":3,"shop_id":5493,"sku_id":6510881,"status":1,"stock":997,"tobacco_alcohol":0,"unit":0,"update_time":"2019.10.07 22:38:03","vat_rate":0.1},{"adjust_price":0.0,"desc":"","first_commodity":"","first_commodity_id":"","group_buy":0,"group_price":0,"id":497201,"image":"https://easi.com.au/static/uploads/photos/p_20180123185440005197.jpg","images":["https://easi.com.au/static/uploads/photos/p_20180123185440005197.jpg"],"is_multiple_sku":false,"is_registered_for_vat":1,"is_sku":1,"is_vat_included":1,"mark_text":"","name":"\u7cef\u7c73\u53c2\u9e21\u6c64","option_groups":[],"org_price":23.8,"price":23.8,"second_commodity":"","second_commodity_id":"","seq":9,"shop_id":5493,"sku_id":6510879,"status":1,"stock":951,"tobacco_alcohol":0,"unit":0,"update_time":"2019.10.07 22:38:03","vat_rate":0.1},{"adjust_price":0.0,"desc":"","first_commodity":"","first_commodity_id":"","group_buy":0,"group_price":0,"id":915029,"image":"https://easi.com.au/static/uploads/photos/p_20181030205903658168.jpg","images":["https://easi.com.au/static/uploads/photos/p_20181030205903658168.jpg"],"is_multiple_sku":false,"is_registered_for_vat":1,"is_sku":1,"is_vat_included":1,"mark_text":"","name":"\u6ce1\u83dc\u8c46\u8150\u6c64","option_groups":[],"org_price":16.8,"price":16.8,"second_commodity":"","second_commodity_id":"","seq":10,"shop_id":5493,"sku_id":6510878,"status":1,"stock":980,"tobacco_alcohol":0,"unit":0,"update_time":"2019.10.07 22:38:03","vat_rate":0.1},{"adjust_price":0.0,"desc":"","first_commodity":"","first_commodity_id":"","group_buy":0,"group_price":0,"id":565030,"image":"https://easi.com.au/static/uploads/photos/p_20181030211204925310.jpg","images":["https://easi.com.au/static/uploads/photos/p_20181030211204925310.jpg"],"is_multiple_sku":false,"is_registered_for_vat":1,"is_sku":1,"is_vat_included":1,"mark_text":"","name":"\u61d2\u4eba\u80a5\u725b","option_groups":[],"org_price":16.8,"price":16.8,"second_commodity":"","second_commodity_id":"","seq":15,"shop_id":5493,"sku_id":6510876,"status":1,"stock":980,"tobacco_alcohol":0,"unit":0,"update_time":"2019.10.07 22:38:03","vat_rate":0.1}],"name":"\u6c64\u6c64\u9505\u9505","seq":3,"shop_id":5493},{"id":51194,"image":"shop-category-default-image.png","items":[{"adjust_price":0.0,"desc":"","first_commodity":"","first_commodity_id":"","group_buy":0,"group_price":0,"id":914962,"image":"https://easi.com.au/static/uploads/photos/s3_c9194829e897a98b035a2655c5e0cefa.jpg","images":["https://easi.com.au/static/uploads/photos/s3_c9194829e897a98b035a2655c5e0cefa.jpg"],"is_multiple_sku":false,"is_registered_for_vat":1,"is_sku":1,"is_vat_included":1,"mark_text":"","name":"\u8fa3\u7092\u9c7f\u9c7c","option_groups":[],"org_price":18.8,"price":18.8,"second_commodity":"","second_commodity_id":"","seq":1,"shop_id":5493,"sku_id":12753067,"status":1,"stock":995,"tobacco_alcohol":0,"unit":0,"update_time":"2019.10.07 22:38:03","vat_rate":0.1},{"adjust_price":0.0,"desc":"","first_commodity":"","first_commodity_id":"","group_buy":0,"group_price":0,"id":565029,"image":"https://easi.com.au/static/uploads/photos/p_20180325185107011824.jpg","images":["https://easi.com.au/static/uploads/photos/p_20180325185107011824.jpg"],"is_multiple_sku":false,"is_registered_for_vat":1,"is_sku":1,"is_vat_included":1,"mark_text":"","name":"\u9999\u714e\u725b\u4ed4\u9aa8","option_groups":[],"org_price":19.8,"price":19.8,"second_commodity":"","second_commodity_id":"","seq":1,"shop_id":5493,"sku_id":6510890,"status":1,"stock":956,"tobacco_alcohol":0,"unit":0,"update_time":"2019.10.07 22:38:03","vat_rate":0.1},{"adjust_price":0.0,"desc":"","first_commodity":"","first_commodity_id":"","group_buy":0,"group_price":0,"id":483792,"image":"https://easi.com.au/static/uploads/photos/s3_1e7488b5d69b4fe22134a0a0a7968f86.jpg","images":["https://easi.com.au/static/uploads/photos/s3_1e7488b5d69b4fe22134a0a0a7968f86.jpg"],"is_multiple_sku":false,"is_registered_for_vat":1,"is_sku":1,"is_vat_included":1,"mark_text":"","name":"Spicy fried Venerupis philippinarum","option_groups":[],"org_price":21.8,"price":21.8,"second_commodity":"","second_commodity_id":"","seq":1,"shop_id":5493,"sku_id":12753070,"status":1,"stock":980,"tobacco_alcohol":0,"unit":0,"update_time":"2019.10.07 22:38:03","vat_rate":0.1},{"adjust_price":0.0,"desc":"","first_commodity":"","first_commodity_id":"","group_buy":0,"group_price":0,"id":483788,"image":"https://easi.com.au/static/uploads/photos/p_20180123211219056074.jpg","images":["https://easi.com.au/static/uploads/photos/p_20180123211219056074.jpg"],"is_multiple_sku":false,"is_registered_for_vat":1,"is_sku":1,"is_vat_included":1,"mark_text":"","name":"\u8fa3\u767d\u83dc\u7092\u4e94\u82b1\u8089","option_groups":[],"org_price":19.8,"price":19.8,"second_commodity":"","second_commodity_id":"","seq":3,"shop_id":5493,"sku_id":6510894,"status":1,"stock":991,"tobacco_alcohol":0,"unit":0,"update_time":"2019.10.07 22:38:03","vat_rate":0.1},{"adjust_price":0.0,"desc":"","first_commodity":"","first_commodity_id":"","group_buy":0,"group_price":0,"id":565022,"image":"https://easi.com.au/static/uploads/photos/s3_2a079064a12040f0e1936ac0156bffc4.jpg","images":["https://easi.com.au/static/uploads/photos/s3_2a079064a12040f0e1936ac0156bffc4.jpg"],"is_multiple_sku":false,"is_registered_for_vat":1,"is_sku":1,"is_vat_included":1,"mark_text":"","name":"\u83dc\u5305\u4e94\u82b1\u8089","option_groups":[],"org_price":21.8,"price":21.8,"second_commodity":"","second_commodity_id":"","seq":4,"shop_id":5493,"sku_id":12753072,"status":1,"stock":974,"tobacco_alcohol":0,"unit":0,"update_time":"2019.10.07 22:38:03","vat_rate":0.1},{"adjust_price":0.0,"desc":"","first_commodity":"","first_commodity_id":"","group_buy":0,"group_price":0,"id":483786,"image":"https://easi.com.au/static/uploads/photos/s3_83197d936e57470cacd1af2a15ba2be4.jpg","images":["https://easi.com.au/static/uploads/photos/s3_83197d936e57470cacd1af2a15ba2be4.jpg"],"is_multiple_sku":false,"is_registered_for_vat":1,"is_sku":1,"is_vat_included":1,"mark_text":"","name":"\u8fa3\u7092\u9c7f\u9c7c","option_groups":[],"org_price":18.8,"price":18.8,"second_commodity":"","second_commodity_id":"","seq":8,"shop_id":5493,"sku_id":12753073,"status":1,"stock":996,"tobacco_alcohol":0,"unit":0,"update_time":"2019.10.07 22:38:03","vat_rate":0.1},{"adjust_price":0.0,"desc":"","first_commodity":"","first_commodity_id":"","group_buy":0,"group_price":0,"id":483790,"image":"https://easi.com.au/static/uploads/photos/p_20180123211339565867.jpg","images":["https://easi.com.au/static/uploads/photos/p_20180123211339565867.jpg"],"is_multiple_sku":false,"is_registered_for_vat":1,"is_sku":1,"is_vat_included":1,"mark_text":"","name":"Fried rice cake","option_groups":[],"org_price":15.8,"price":15.8,"second_commodity":"","second_commodity_id":"","seq":12,"shop_id":5493,"sku_id":6510913,"status":1,"stock":983,"tobacco_alcohol":0,"unit":0,"update_time":"2019.10.07 22:38:03","vat_rate":0.1}],"name":"\u7cbe\u54c1\u70ed\u83dc","seq":4,"shop_id":5493},{"id":51193,"image":"shop-category-default-image.png","items":[{"adjust_price":0.0,"desc":"","first_commodity":"","first_commodity_id":"","group_buy":0,"group_price":0,"id":565073,"image":"https://easi.com.au/static/uploads/photos/p_20180325230536149273.jpg","images":["https://easi.com.au/static/uploads/photos/p_20180325230536149273.jpg"],"is_multiple_sku":false,"is_registered_for_vat":1,"is_sku":1,"is_vat_included":1,"mark_text":"","name":"\u8fa3\u767d\u83dc","option_groups":[],"org_price":3.8,"price":3.8,"second_commodity":"","second_commodity_id":"","seq":1,"shop_id":5493,"sku_id":6510918,"status":1,"stock":967,"tobacco_alcohol":0,"unit":0,"update_time":"2019.10.07 22:38:03","vat_rate":0.1},{"adjust_price":0.0,"desc":"","first_commodity":"","first_commodity_id":"","group_buy":0,"group_price":0,"id":483795,"image":"https://easi.com.au/static/uploads/photos/s3_dc7f46caaa55bd4e5998f59bc167f0bc.jpg","images":["https://easi.com.au/static/uploads/photos/s3_dc7f46caaa55bd4e5998f59bc167f0bc.jpg"],"is_multiple_sku":false,"is_registered_for_vat":1,"is_sku":1,"is_vat_included":1,"mark_text":"","name":"\u62cc\u82b1\u86e4\u8089","option_groups":[],"org_price":16.8,"price":16.8,"second_commodity":"","second_commodity_id":"","seq":15,"shop_id":5493,"sku_id":12753057,"status":1,"stock":991,"tobacco_alcohol":0,"unit":0,"update_time":"2019.10.07 22:38:03","vat_rate":0.1},{"adjust_price":0.0,"desc":"","first_commodity":"","first_commodity_id":"","group_buy":0,"group_price":0,"id":483796,"image":"https://easi.com.au/static/uploads/photos/s3_29a1cab9eb9b63217fab6403a6b0a948.jpg","images":["https://easi.com.au/static/uploads/photos/s3_29a1cab9eb9b63217fab6403a6b0a948.jpg"],"is_multiple_sku":false,"is_registered_for_vat":1,"is_sku":1,"is_vat_included":1,"mark_text":"","name":"\u8fa3\u62cc\u9c7f\u9c7c","option_groups":[],"org_price":16.8,"price":16.8,"second_commodity":"","second_commodity_id":"","seq":16,"shop_id":5493,"sku_id":12753058,"status":1,"stock":990,"tobacco_alcohol":0,"unit":0,"update_time":"2019.10.07 22:38:03","vat_rate":0.1}],"name":"\u723d\u53e3\u51c9\u83dc","seq":5,"shop_id":5493},{"id":51195,"image":"shop-category-default-image.png","items":[{"adjust_price":0.0,"desc":"","first_commodity":"","first_commodity_id":"","group_buy":0,"group_price":0,"id":497750,"image":"https://easi.com.au/static/uploads/photos/p_20180123213359257422.jpg","images":["https://easi.com.au/static/uploads/photos/p_20180123213359257422.jpg"],"is_multiple_sku":false,"is_registered_for_vat":1,"is_sku":1,"is_vat_included":1,"mark_text":"","name":"\u6bdb\u8c46","option_groups":[],"org_price":3.9,"price":3.9,"second_commodity":"","second_commodity_id":"","seq":24,"shop_id":5493,"sku_id":6510924,"status":1,"stock":985,"tobacco_alcohol":0,"unit":0,"update_time":"2019.10.07 22:38:03","vat_rate":0.1},{"adjust_price":0.0,"desc":"","first_commodity":"","first_commodity_id":"","group_buy":0,"group_price":0,"id":497751,"image":"https://easi.com.au/static/uploads/photos/s3_8e85646983993a4c6dc64ed21466d42e.jpg","images":["https://easi.com.au/static/uploads/photos/s3_8e85646983993a4c6dc64ed21466d42e.jpg"],"is_multiple_sku":false,"is_registered_for_vat":1,"is_sku":1,"is_vat_included":1,"mark_text":"","name":"\u7ae0\u9c7c\u5c0f\u4e38\u5b50","option_groups":[],"org_price":5.9,"price":5.9,"second_commodity":"","second_commodity_id":"","seq":25,"shop_id":5493,"sku_id":8040098,"status":1,"stock":904,"tobacco_alcohol":0,"unit":0,"update_time":"2019.10.07 22:38:03","vat_rate":0.1},{"adjust_price":0.0,"desc":"","first_commodity":"","first_commodity_id":"","group_buy":0,"group_price":0,"id":497746,"image":"https://easi.com.au/static/uploads/photos/p_20180123213106615929.jpg","images":["https://easi.com.au/static/uploads/photos/p_20180123213106615929.jpg"],"is_multiple_sku":false,"is_registered_for_vat":1,"is_sku":1,"is_vat_included":1,"mark_text":"","name":"\u65e5\u5f0f\u70b8\u867e","option_groups":[],"org_price":5.9,"price":5.9,"second_commodity":"","second_commodity_id":"","seq":27,"shop_id":5493,"sku_id":6510929,"status":1,"stock":987,"tobacco_alcohol":0,"unit":0,"update_time":"2019.10.07 22:38:03","vat_rate":0.1},{"adjust_price":0.0,"desc":"","first_commodity":"","first_commodity_id":"","group_buy":0,"group_price":0,"id":497747,"image":"https://easi.com.au/static/uploads/photos/p_20180123213131697534.jpg","images":["https://easi.com.au/static/uploads/photos/p_20180123213131697534.jpg"],"is_multiple_sku":false,"is_registered_for_vat":1,"is_sku":1,"is_vat_included":1,"mark_text":"","name":"\u65e5\u5f0f\u714e\u997a","option_groups":[],"org_price":6.9,"price":6.9,"second_commodity":"","second_commodity_id":"","seq":28,"shop_id":5493,"sku_id":6510931,"status":1,"stock":964,"tobacco_alcohol":0,"unit":0,"update_time":"2019.10.07 22:38:03","vat_rate":0.1},{"adjust_price":0.0,"desc":"","first_commodity":"","first_commodity_id":"","group_buy":0,"group_price":0,"id":497748,"image":"https://easi.com.au/static/uploads/photos/p_20180123213152613194.jpg","images":["https://easi.com.au/static/uploads/photos/p_20180123213152613194.jpg"],"is_multiple_sku":false,"is_registered_for_vat":1,"is_sku":1,"is_vat_included":1,"mark_text":"","name":"\u5927\u962a\u70e7","option_groups":[],"org_price":6.9,"price":6.9,"second_commodity":"","second_commodity_id":"","seq":29,"shop_id":5493,"sku_id":6510934,"status":1,"stock":970,"tobacco_alcohol":0,"unit":0,"update_time":"2019.10.07 22:38:03","vat_rate":0.1},{"adjust_price":0.0,"desc":"","first_commodity":"","first_commodity_id":"","group_buy":0,"group_price":0,"id":497749,"image":"https://easi.com.au/static/uploads/photos/p_20180123213246222102.jpg","images":["https://easi.com.au/static/uploads/photos/p_20180123213246222102.jpg"],"is_multiple_sku":false,"is_registered_for_vat":1,"is_sku":1,"is_vat_included":1,"mark_text":"","name":"\u9ec4\u91d1\u87f9\u94b3","option_groups":[],"org_price":6.9,"price":6.9,"second_commodity":"","second_commodity_id":"","seq":30,"shop_id":5493,"sku_id":6510936,"status":1,"stock":959,"tobacco_alcohol":0,"unit":0,"update_time":"2019.10.07 22:38:03","vat_rate":0.1}],"name":"\u65e5\u5f0f\u5c0f\u98df","seq":6,"shop_id":5493},{"id":51196,"image":"shop-category-default-image.png","items":[{"adjust_price":0.0,"desc":"","first_commodity":"","first_commodity_id":"","group_buy":0,"group_price":0,"id":483777,"image":"https://easi.com.au/static/uploads/photos/p_20180123190046538874.jpg","images":["https://easi.com.au/static/uploads/photos/p_20180123190046538874.jpg"],"is_multiple_sku":false,"is_registered_for_vat":1,"is_sku":1,"is_vat_included":1,"mark_text":"","name":"\u8fa3\u767d\u83dc\u997c","option_groups":[],"org_price":14.8,"price":14.8,"second_commodity":"","second_commodity_id":"","seq":7,"shop_id":5493,"sku_id":6510941,"status":1,"stock":982,"tobacco_alcohol":0,"unit":0,"update_time":"2019.10.07 22:38:03","vat_rate":0.1},{"adjust_price":0.0,"desc":"","first_commodity":"","first_commodity_id":"","group_buy":0,"group_price":0,"id":483782,"image":"https://easi.com.au/static/uploads/photos/p_20180123211103331175.jpg","images":["https://easi.com.au/static/uploads/photos/p_20180123211103331175.jpg"],"is_multiple_sku":false,"is_registered_for_vat":1,"is_sku":1,"is_vat_included":1,"mark_text":"","name":"\u8fa3\u9c7f\u9c7c\u7092\u996d","option_groups":[],"org_price":14.8,"price":14.8,"second_commodity":"","second_commodity_id":"","seq":9,"shop_id":5493,"sku_id":6510946,"status":1,"stock":951,"tobacco_alcohol":0,"unit":0,"update_time":"2019.10.07 22:38:03","vat_rate":0.1},{"adjust_price":0.0,"desc":"","first_commodity":"","first_commodity_id":"","group_buy":0,"group_price":0,"id":483780,"image":"https://easi.com.au/static/uploads/photos/p_20180325212429039733.jpg","images":["https://easi.com.au/static/uploads/photos/p_20180325212429039733.jpg"],"is_multiple_sku":false,"is_registered_for_vat":1,"is_sku":1,"is_vat_included":1,"mark_text":"","name":"\u8fa3\u767d\u83dc\u7092\u996d","option_groups":[],"org_price":14.8,"price":14.8,"second_commodity":"","second_commodity_id":"","seq":10,"shop_id":5493,"sku_id":6510947,"status":1,"stock":927,"tobacco_alcohol":0,"unit":0,"update_time":"2019.10.07 22:38:03","vat_rate":0.1},{"adjust_price":0.0,"desc":"","first_commodity":"","first_commodity_id":"","group_buy":0,"group_price":0,"id":483781,"image":"https://easi.com.au/static/uploads/photos/s3_c35df284ee7e11e9b3df02d230943746.jpg","images":["https://easi.com.au/static/uploads/photos/s3_c35df284ee7e11e9b3df02d230943746.jpg"],"is_multiple_sku":false,"is_registered_for_vat":0,"is_sku":1,"is_vat_included":1,"mark_text":"","name":"\u4ec0\u9526\u86cb\u7092\u996d","option_groups":[],"org_price":11.8,"price":11.8,"second_commodity":"","second_commodity_id":"","seq":11,"shop_id":5493,"sku_id":6992393,"status":1,"stock":944,"tobacco_alcohol":0,"unit":0,"update_time":"2019.10.07 22:38:03","vat_rate":0.1},{"adjust_price":0.0,"desc":"","first_commodity":"","first_commodity_id":"","group_buy":0,"group_price":0,"id":483784,"image":"https://easi.com.au/static/uploads/photos/p_20180116115754742435.jpg","images":["https://easi.com.au/static/uploads/photos/p_20180116115754742435.jpg"],"is_multiple_sku":false,"is_registered_for_vat":1,"is_sku":1,"is_vat_included":1,"mark_text":"","name":"\u8001\u5f0f\u62cc\u996d","option_groups":[],"org_price":10.8,"price":10.8,"second_commodity":"","second_commodity_id":"","seq":12,"shop_id":5493,"sku_id":6510956,"status":1,"stock":931,"tobacco_alcohol":0,"unit":0,"update_time":"2019.10.07 22:38:03","vat_rate":0.1},{"adjust_price":0.0,"desc":"","first_commodity":"","first_commodity_id":"","group_buy":0,"group_price":0,"id":483785,"image":"https://easi.com.au/static/uploads/photos/p_20180123211051258465.jpg","images":["https://easi.com.au/static/uploads/photos/p_20180123211051258465.jpg"],"is_multiple_sku":false,"is_registered_for_vat":1,"is_sku":1,"is_vat_included":1,"mark_text":"","name":"\u9505\u5e95\u8f9b\u62c9\u9762","option_groups":[],"org_price":11.8,"price":11.8,"second_commodity":"","second_commodity_id":"","seq":12,"shop_id":5493,"sku_id":6510960,"status":1,"stock":970,"tobacco_alcohol":0,"unit":0,"update_time":"2019.10.07 22:38:03","vat_rate":0.1},{"adjust_price":0.0,"desc":"","first_commodity":"","first_commodity_id":"","group_buy":0,"group_price":0,"id":901559,"image":"https://easi.com.au/static/uploads/photos/p_20190429180440410473.jpg","images":["https://easi.com.au/static/uploads/photos/p_20190429180440410473.jpg"],"is_multiple_sku":false,"is_registered_for_vat":1,"is_sku":1,"is_vat_included":1,"mark_text":"","name":"\u4f60\u4ece\u672a\u5403\u8fc7\u7684\u7092\u62c9\u9762","option_groups":[],"org_price":15.8,"price":15.8,"second_commodity":"","second_commodity_id":"","seq":42,"shop_id":5493,"sku_id":6510966,"status":1,"stock":947,"tobacco_alcohol":0,"unit":0,"update_time":"2019.10.07 22:38:03","vat_rate":0.1},{"adjust_price":0.0,"desc":"","first_commodity":"","first_commodity_id":"","group_buy":0,"group_price":0,"id":915040,"image":"https://easi.com.au/static/uploads/photos/s3_c0bc3a57758fcee1f353e0132afb57f9.jpg","images":["https://easi.com.au/static/uploads/photos/s3_c0bc3a57758fcee1f353e0132afb57f9.jpg"],"is_multiple_sku":false,"is_registered_for_vat":1,"is_sku":1,"is_vat_included":1,"mark_text":"","name":"rice","option_groups":[],"org_price":2.5,"price":2.5,"second_commodity":"","second_commodity_id":"","seq":9988,"shop_id":5493,"sku_id":12753062,"status":1,"stock":913,"tobacco_alcohol":0,"unit":0,"update_time":"2019.10.07 22:38:03","vat_rate":0.1}],"name":"\u7092\u996d\u9762\u98df","seq":7,"shop_id":5493},{"id":51197,"image":"shop-category-default-image.png","items":[{"adjust_price":0.0,"desc":"","first_commodity":"","first_commodity_id":"","group_buy":0,"group_price":0,"id":497756,"image":"https://easi.com.au/static/uploads/photos/p_20180123220340699249.png","images":["https://easi.com.au/static/uploads/photos/p_20180123220340699249.png"],"is_multiple_sku":false,"is_registered_for_vat":1,"is_sku":1,"is_vat_included":1,"mark_text":"","name":"Calpis Water","option_groups":[],"org_price":3.5,"price":3.5,"second_commodity":"","second_commodity_id":"","seq":1,"shop_id":5493,"sku_id":6510971,"status":1,"stock":987,"tobacco_alcohol":0,"unit":0,"update_time":"2020.04.13 14:55:38","vat_rate":0.1},{"adjust_price":0.0,"desc":"","first_commodity":"","first_commodity_id":"","group_buy":0,"group_price":0,"id":915042,"image":"https://easi.com.au/static/uploads/photos/p_20181030210530955583.jpg","images":["https://easi.com.au/static/uploads/photos/p_20181030210530955583.jpg"],"is_multiple_sku":false,"is_registered_for_vat":1,"is_sku":1,"is_vat_included":1,"mark_text":"","name":"Milkis","option_groups":[],"org_price":3.5,"price":3.5,"second_commodity":"","second_commodity_id":"","seq":1,"shop_id":5493,"sku_id":6494344,"status":1,"stock":950,"tobacco_alcohol":0,"unit":0,"update_time":"2019.10.07 22:38:03","vat_rate":0.1},{"adjust_price":0.0,"desc":"","first_commodity":"","first_commodity_id":"","group_buy":0,"group_price":0,"id":915047,"image":"https://easi.com.au/static/uploads/photos/p_20181030210949301481.jpg","images":["https://easi.com.au/static/uploads/photos/p_20181030210949301481.jpg"],"is_multiple_sku":false,"is_registered_for_vat":1,"is_sku":1,"is_vat_included":1,"mark_text":"","name":"Coke","option_groups":[],"org_price":3.5,"price":3.5,"second_commodity":"","second_commodity_id":"","seq":1,"shop_id":5493,"sku_id":6494345,"status":1,"stock":976,"tobacco_alcohol":0,"unit":0,"update_time":"2019.10.07 22:38:03","vat_rate":0.1},{"adjust_price":0.0,"desc":"","first_commodity":"","first_commodity_id":"","group_buy":0,"group_price":0,"id":915046,"image":"https://easi.com.au/static/uploads/photos/p_20181030210811335940.jpg","images":["https://easi.com.au/static/uploads/photos/p_20181030210811335940.jpg"],"is_multiple_sku":false,"is_registered_for_vat":1,"is_sku":1,"is_vat_included":1,"mark_text":"","name":"Spirte","option_groups":[],"org_price":3.5,"price":3.5,"second_commodity":"","second_commodity_id":"","seq":2,"shop_id":5493,"sku_id":6494346,"status":1,"stock":995,"tobacco_alcohol":0,"unit":0,"update_time":"2019.10.07 22:38:03","vat_rate":0.1},{"adjust_price":0.0,"desc":"","first_commodity":"","first_commodity_id":"","group_buy":0,"group_price":0,"id":915045,"image":"https://easi.com.au/static/uploads/photos/p_20181030210751095489.jpg","images":["https://easi.com.au/static/uploads/photos/p_20181030210751095489.jpg"],"is_multiple_sku":false,"is_registered_for_vat":1,"is_sku":1,"is_vat_included":1,"mark_text":"","name":"Fanta","option_groups":[],"org_price":3.5,"price":3.5,"second_commodity":"","second_commodity_id":"","seq":3,"shop_id":5493,"sku_id":6494347,"status":1,"stock":994,"tobacco_alcohol":0,"unit":0,"update_time":"2019.10.07 22:38:03","vat_rate":0.1},{"adjust_price":0.0,"desc":"","first_commodity":"","first_commodity_id":"","group_buy":0,"group_price":0,"id":1288921,"image":"https://easi.com.au/static/uploads/photos/s3_7f2a53a2763111e9acd3029e78e161bc.jpg","images":["https://easi.com.au/static/uploads/photos/s3_7f2a53a2763111e9acd3029e78e161bc.jpg"],"is_multiple_sku":false,"is_registered_for_vat":1,"is_sku":1,"is_vat_included":1,"mark_text":"","name":"\u756a\u77f3\u69b4\u6c41","option_groups":[],"org_price":3.8,"price":3.8,"second_commodity":"","second_commodity_id":"","seq":10,"shop_id":5493,"sku_id":6511020,"status":1,"stock":996,"tobacco_alcohol":0,"unit":0,"update_time":"2020.04.13 14:55:44","vat_rate":0.1},{"adjust_price":0.0,"desc":"","first_commodity":"","first_commodity_id":"","group_buy":0,"group_price":0,"id":1288922,"image":"https://easi.com.au/static/uploads/photos/s3_88c36070763111e9baec0a89c8d8c336.jpg","images":["https://easi.com.au/static/uploads/photos/s3_88c36070763111e9baec0a89c8d8c336.jpg"],"is_multiple_sku":false,"is_registered_for_vat":1,"is_sku":1,"is_vat_included":1,"mark_text":"","name":"\u6728\u74dc\u725b\u5976","option_groups":[],"org_price":3.8,"price":3.8,"second_commodity":"","second_commodity_id":"","seq":11,"shop_id":5493,"sku_id":6511025,"status":1,"stock":993,"tobacco_alcohol":0,"unit":0,"update_time":"2019.10.07 22:38:03","vat_rate":0.1},{"adjust_price":0.0,"desc":"","first_commodity":"","first_commodity_id":"","group_buy":0,"group_price":0,"id":1396871,"image":"https://easi.com.au/static/uploads/photos/s3_70e5e148a32311e98d080a04ee6b6cc6.jpg","images":["https://easi.com.au/static/uploads/photos/s3_70e5e148a32311e98d080a04ee6b6cc6.jpg"],"is_multiple_sku":false,"is_registered_for_vat":1,"is_sku":1,"is_vat_included":1,"mark_text":"","name":"Banana milk","option_groups":[],"org_price":3.8,"price":3.8,"second_commodity":"","second_commodity_id":"","seq":46,"shop_id":5493,"sku_id":6511029,"status":1,"stock":990,"tobacco_alcohol":0,"unit":0,"update_time":"2019.10.07 22:38:03","vat_rate":0.1},{"adjust_price":0.0,"desc":"","first_commodity":"","first_commodity_id":"","group_buy":0,"group_price":0,"id":1389039,"image":"https://easi.com.au/static/uploads/photos/s3_5b23b50e9e3911e98e9a0ab95a52d3ac.jpg","images":["https://easi.com.au/static/uploads/photos/s3_5b23b50e9e3911e98e9a0ab95a52d3ac.jpg"],"is_multiple_sku":false,"is_registered_for_vat":1,"is_sku":1,"is_vat_included":1,"mark_text":"","name":"Winter melon tea","option_groups":[],"org_price":3.8,"price":3.8,"second_commodity":"","second_commodity_id":"","seq":9994,"shop_id":5493,"sku_id":6511031,"status":1,"stock":992,"tobacco_alcohol":0,"unit":0,"update_time":"2019.10.07 22:38:03","vat_rate":0.1}],"name":"\u6e05\u51c9\u996e\u54c1","seq":8,"shop_id":5493}],"shop_info":{"addr":"167 Gouger Street, Adelaide, SA, 5000, Australia","addr_remark":"","allow_pickup":1,"average_amount":null,"avg_score":4.5,"brief_info":"281 sold","business":0,"business_info":{"is_business":false,"is_can_make_order":false,"text":"Tomorrow 17:00 Open for business"},"cash_discount":null,"contact_number":"0406900666","coupons":[],"currency_symbol":"$","delivery_fee_discount":0.0,"delivery_fee_discount_condition":0.0,"delivery_fee_discount_type":0,"delivery_type":0,"desc":"","discount":0.1,"discount_type":1,"distance_text":"45 Mins Delivery","exclusive":null,"has_coupon":false,"has_delivery_fee_discount":0,"has_discount":false,"hot_sale":null,"id":5493,"image":"https://easi.com.au/static/uploads/photos/s3_e82bc69a7d3b11e996c70a21553f9bde.jpeg","is_self_pick":true,"is_support_delivery":true,"is_third_delivery_fee":false,"is_vat_included":true,"location":"-34.9307501,138.59291480000002","merchant_coupon":{"items":[],"total_fee":0},"name":"Lazy Nabe","new_arrival":null,"next_business_time":"Tomorrow 17:00 ","payment_info":{"payment_type":1,"payment_type_name":"Pay Online"},"pickup_type":0,"platform_settlement_status":null,"points":4.6,"points_text":"4.6","ratings":null,"real_contact_number":"0406900666","recommend":null,"reviews_count":10,"seq":74,"shop_area_id":26,"shop_order_fee_discount":0.0,"shop_style_id":119,"shop_type":"restaurant","threshold_amount":0.0,"today_business_time":"No business today","type":1,"update_time":"2020.04.20 11:41:58","vat_rate":0.1}}}
